kafkapy/__init__.py
kafkapy/__main__.py
kafkapy/__version__.py
kafkapy/acls.py
kafkapy/brokers.py
kafkapy/callbacks.py
kafkapy/client/__init__.py
kafkapy/client/client.py
kafkapy/client/models.py
kafkapy/client/protocols.py
kafkapy/constants.py
kafkapy/consumer_groups.py
kafkapy/help.py
kafkapy/main.py
kafkapy/options.py
kafkapy/out.py
kafkapy/parsers.py
kafkapy/properties.py
kafkapy/styles.py
kafkapy/topics.py
kafkapy/types.py
kafkapy/utils.py
kafkapy-0.3.1.dist-info/LICENSE
kafkapy-0.3.1.dist-info/METADATA
kafkapy-0.3.1.dist-info/WHEEL
kafkapy-0.3.1.dist-info/entry_points.txt
kafkapy-0.3.1.dist-info/RECORD
