Metadata-Version: 2.1
Name: kafkapy
Version: 0.3.1
Summary: Python CLI for managing a kafka cluster
Author: symonk
Author-email: jackofspaces@gmail.com
Requires-Python: >=3.8,<4.0
Classifier: Programming Language :: Python :: 3
Classifier: Programming Language :: Python :: 3.8
Classifier: Programming Language :: Python :: 3.9
Classifier: Programming Language :: Python :: 3.10
Classifier: Programming Language :: Python :: 3.11
Classifier: Programming Language :: Python :: 3.12
Requires-Dist: confluent-kafka (>=2.3.0,<3.0.0)
Requires-Dist: pydantic (>=2.5.3,<3.0.0)
Requires-Dist: pyyaml (>=6.0.1,<7.0.0)
Requires-Dist: rich (>=13.7.0,<14.0.0)
Requires-Dist: typer[all] (>=0.9.0,<0.10.0)
